{"name":"Get All Class with Authorization","id":"get-all-class;get-all-class-with-authorization","testSteps":[{"number":1,"description":"Given User login with valid data","duration":11,"startTime":"2022-11-14T04:56:37.876+07:00[Asia/Bangkok]","result":"SUCCESS","precondition":false,"level":0,"children":[{"number":2,"description":"Login Admin Background","duration":1,"startTime":"2022-11-14T04:56:37.884+07:00[Asia/Bangkok]","result":"SUCCESS","precondition":false,"level":1}]},{"number":3,"description":"When Send request post login user","duration":837,"startTime":"2022-11-14T04:56:37.890+07:00[Asia/Bangkok]","result":"SUCCESS","precondition":false,"level":0,"children":[{"number":4,"description":"POST https://ecommerce-alta.online/login\r","duration":1,"startTime":"2022-11-14T04:56:38.725+07:00[Asia/Bangkok]","result":"SUCCESS","restQuery":{"method":"POST","path":"https://ecommerce-alta.online/login\r","content":"C:\\Users\\HP\\Downloads\\Apih\\dibakar\\QE-API\\src\\test\\resources\\JSON\\LoginAdminBackground.json\r","contentType":"application/json","requestHeaders":"Accept\u003d*/*\r\n\t\t\t\tContent-Type\u003dapplication/json; charset\u003dUTF-8\r","requestCookies":"\r","responseHeaders":"Date: Sun, 13 Nov 2022 21:56:40 GMT\r\nContent-Type: application/json; charset\u003dUTF-8\r\nTransfer-Encoding: chunked\r\nConnection: keep-alive\r\nVary: Origin\r\nCF-Cache-Status: DYNAMIC\r\nReport-To: {\"endpoints\":[{\"url\":\"https:\\/\\/a.nel.cloudflare.com\\/report\\/v3?s\u003dKukQDIg0y%2FrzJIgHNZbyvQxJvauRQd3ElVLp1JJPXHtCo70dfND0VawRV%2BBZMeE%2Fr7vbJGovwtiC5zOO8W1Gt7f7Wae2aQUjvUC1GS779sttGUxN%2F8uaxAcITYtjZVTV036T7eJX%2BXY%3D\"}],\"group\":\"cf-nel\",\"max_age\":604800}\r\nNEL: {\"success_fraction\":0,\"report_to\":\"cf-nel\",\"max_age\":604800}\r\nServer: cloudflare\r\nCF-RAY: 769ac239cbae7eb4-LAX\r\nContent-Encoding: gzip\r\nalt-svc: h3\u003d\":443\"; ma\u003d86400, h3-29\u003d\":443\"; ma\u003d86400\r","responseCookies":"\r","responseBody":"{\n    \"data\": {\n        \"id_user\": 1000,\n        \"name\": \"Admin Mentutor\",\n        \"email\": \"admin.mentutor@gmail.com\",\n        \"id_class\": 0,\n        \"class_name\": \"\",\n        \"role\": \"admin\",\n        \"images\": \"\",\n        \"token\": \"eyJhbGciOiJIUzI1NiIsInR5cCI6IkpXVCJ9.eyJJZENsYXNzIjowLCJhdXRob3JpemVkIjp0cnVlLCJleHAiOjE2NjgzODM4MDAsInJvbGUiOiJhZG1pbiIsInVzZXJJZCI6MTAwMH0.SoBGOVV_454WuubzZeb_Cdyr-KSansvSw0iSTBVkn90\",\n        \"auth_gmail\": \"\"\n    },\n    \"message\": \"login successful\"\n}","statusCode":200},"precondition":false,"level":1}]},{"number":5,"description":"And Set token to Admin Token","duration":17,"startTime":"2022-11-14T04:56:38.728+07:00[Asia/Bangkok]","result":"SUCCESS","precondition":false,"level":0},{"number":6,"description":"Given Get all class using valid path with authorization","duration":10,"startTime":"2022-11-14T04:56:38.746+07:00[Asia/Bangkok]","result":"SUCCESS","precondition":false,"level":0,"children":[{"number":7,"description":"Get All Class","duration":3,"startTime":"2022-11-14T04:56:38.751+07:00[Asia/Bangkok]","result":"SUCCESS","precondition":false,"level":1}]},{"number":8,"description":"When Send request get all class","duration":1702,"startTime":"2022-11-14T04:56:38.756+07:00[Asia/Bangkok]","result":"SUCCESS","precondition":false,"level":0,"children":[{"number":9,"description":"GET https://ecommerce-alta.online/admin/classes\r","duration":0,"startTime":"2022-11-14T04:56:40.457+07:00[Asia/Bangkok]","result":"SUCCESS","restQuery":{"method":"GET","path":"https://ecommerce-alta.online/admin/classes\r","content":"\r","contentType":"null","requestHeaders":"Authorization\u003dBearer eyJhbGciOiJIUzI1NiIsInR5cCI6IkpXVCJ9.eyJJZENsYXNzIjowLCJhdXRob3JpemVkIjp0cnVlLCJleHAiOjE2NjgzODM4MDAsInJvbGUiOiJhZG1pbiIsInVzZXJJZCI6MTAwMH0.SoBGOVV_454WuubzZeb_Cdyr-KSansvSw0iSTBVkn90\r\n\t\t\t\tAccept\u003d*/*\r","requestCookies":"\r","responseHeaders":"Date: Sun, 13 Nov 2022 21:56:42 GMT\r\nContent-Type: application/json; charset\u003dUTF-8\r\nTransfer-Encoding: chunked\r\nConnection: keep-alive\r\nVary: Origin\r\nCF-Cache-Status: DYNAMIC\r\nReport-To: {\"endpoints\":[{\"url\":\"https:\\/\\/a.nel.cloudflare.com\\/report\\/v3?s\u003dLjzYD99sMTQJwYCuqhbTSYtlH0mpTzvSvaMxJMqooPsVziuw7W8y7lKkPGEcrC%2BjkrxK48n55VIQziQK2j8hKbmV5H3A9BM%2BwrfbPtFgmrb33VKvvnPt5d6W2RjIbpPqjxYVKMeRRiQ%3D\"}],\"group\":\"cf-nel\",\"max_age\":604800}\r\nNEL: {\"success_fraction\":0,\"report_to\":\"cf-nel\",\"max_age\":604800}\r\nServer: cloudflare\r\nCF-RAY: 769ac2448a027b5d-LAX\r\nContent-Encoding: gzip\r\nalt-svc: h3\u003d\":443\"; ma\u003d86400, h3-29\u003d\":443\"; ma\u003d86400\r","responseCookies":"\r","responseBody":"{\n    \"data\": [\n        {\n            \"id_class\": 1,\n            \"class_name\": \"Back End\",\n            \"status\": \"active\",\n            \"total_student\": 4\n        },\n        {\n            \"id_class\": 2,\n            \"class_name\": \"Base Testing\",\n            \"status\": \"active\",\n            \"total_student\": 3\n        },\n        {\n            \"id_class\": 3,\n            \"class_name\": \"Front End\",\n            \"status\": \"active\",\n            \"total_student\": 6\n        },\n        {\n            \"id_class\": 6,\n            \"class_name\": \"Kelas Fordelete\",\n            \"status\": \"active\",\n            \"total_student\": 0\n        },\n        {\n            \"id_class\": 8,\n            \"class_name\": \"Kelas Untuk di Edit\",\n            \"status\": \"active\",\n            \"total_student\": 0\n        },\n        {\n            \"id_class\": 11,\n            \"class_name\": \"Bahasa kalbu\",\n            \"status\": \"non_active\",\n            \"total_student\": 0\n        },\n        {\n            \"id_class\": 12,\n            \"class_name\": \"Bahasa Portugal\",\n            \"status\": \"active\",\n            \"total_student\": 0\n        },\n        {\n            \"id_class\": 14,\n            \"class_name\": \"Bahasa Inggris\",\n            \"status\": \"active\",\n            \"total_student\": 0\n        },\n        {\n            \"id_class\": 17,\n            \"class_name\": \"Bahasa Ayah\",\n            \"status\": \"active\",\n            \"total_student\": 0\n        },\n        {\n            \"id_class\": 19,\n            \"class_name\": \"Bahasa Taiwan\",\n            \"status\": \"active\",\n            \"total_student\": 0\n        }\n    ],\n    \"message\": \"Success Get All Class\"\n}","statusCode":200},"precondition":false,"level":1}]},{"number":10,"description":"Then Should return status code 200 OK","duration":6,"startTime":"2022-11-14T04:56:40.459+07:00[Asia/Bangkok]","result":"SUCCESS","precondition":false,"level":0}],"userStory":{"id":"get-all-class","storyName":"Get All Class","path":"classpath:features/Admin/GetAllClass.feature","type":"feature"},"featureTag":{"name":"Admin/Get All Class","type":"feature","displayName":"Admin/Get All Class"},"title":"Get All Class with Authorization","description":"","backgroundTitle":"Login Admin","backgroundDescription":"","tags":[{"name":"Tamara","type":"tag","displayName":"Tamara"},{"name":"Admin/Get All Class","type":"feature","displayName":"Get All Class"},{"name":"Admin","type":"capability","displayName":"Admin"}],"startTime":"2022-11-14T04:56:37.869+07:00[Asia/Bangkok]","duration":2597,"projectKey":"","isManualTestingUpToDate":false,"manual":false,"testSource":"Cucumber","result":"SUCCESS"}